{"cameraMode":{"drawMode":0,"name":"Shaded","section":"Shading Mode"},"sceneLighting":true,"audioPlay":false,"sceneViewState":{"m_AlwaysRefresh":false,"showFog":true,"showSkybox":true,"showFlares":true,"showImageEffects":true,"showParticleSystems":true,"showVisualEffectGraphs":true,"m_FxEnabled":true},"in2DMode":false,"pivot":{"x":3.694371223449707,"y":0.45758819580078127,"z":-2.344623565673828},"rotation":{"x":0.623101532459259,"y":0.171195849776268,"z":-0.142250195145607,"w":0.7498995065689087},"size":31.69761848449707,"orthographic":false}